tts_webui_extension/tortoise_tts/TortoiseParameters.py
tts_webui_extension/tortoise_tts/__init__.py
tts_webui_extension/tortoise_tts/api.py
tts_webui_extension/tortoise_tts/autoregressive_params.py
tts_webui_extension/tortoise_tts/diffusion_params.py
tts_webui_extension/tortoise_tts/main.py
tts_webui_extension/tortoise_tts/presets.py
tts_webui_extension/tortoise_tts/save_json.py
tts_webui_extension/tortoise_tts/tortoise_model_settings_ui.py
tts_webui_extension_tortoise_tts-0.0.5.dist-info/licenses/LICENSE
tts_webui_extension_tortoise_tts-0.0.5.dist-info/METADATA
tts_webui_extension_tortoise_tts-0.0.5.dist-info/WHEEL
tts_webui_extension_tortoise_tts-0.0.5.dist-info/top_level.txt
tts_webui_extension_tortoise_tts-0.0.5.dist-info/RECORD
