Metadata-Version: 2.4
Name: tts_webui_extension.tortoise_tts
Version: 0.0.5
Summary: Tortoise TTS is a high-quality text-to-speech model with voice cloning capabilities
Home-page: https://github.com/rsxdalv/tts_webui_extension.tortoise_tts
Author: rsxdalv
Classifier: Programming Language :: Python :: 3
Classifier: License :: OSI Approved :: MIT License
Classifier: Operating System :: OS Independent
License-File: LICENSE
Requires-Dist: tts-webui.tortoise-tts
Dynamic: author
Dynamic: classifier
Dynamic: description
Dynamic: description-content-type
Dynamic: home-page
Dynamic: license-file
Dynamic: requires-dist
Dynamic: summary
